{
  "nodes": [
    {
      "id": "src_abstracts_abstractmap_ts",
      "label": "AbstractMap.ts",
      "file_type": "code",
      "source_file": "src\\abstracts\\AbstractMap.ts",
      "source_location": "L1"
    },
    {
      "id": "abstractmap_constructor",
      "label": "constructor()",
      "file_type": "code",
      "source_file": "src\\abstracts\\AbstractMap.ts",
      "source_location": "L119"
    },
    {
      "id": "abstractmap_length",
      "label": "length()",
      "file_type": "code",
      "source_file": "src\\abstracts\\AbstractMap.ts",
      "source_location": "L147"
    },
    {
      "id": "abstractmap_putall",
      "label": "putAll()",
      "file_type": "code",
      "source_file": "src\\abstracts\\AbstractMap.ts",
      "source_location": "L229"
    },
    {
      "id": "abstractmap_validatekeytype",
      "label": "validateKeyType()",
      "file_type": "code",
      "source_file": "src\\abstracts\\AbstractMap.ts",
      "source_location": "L248"
    },
    {
      "id": "abstractmap_validatevaluetype",
      "label": "validateValueType()",
      "file_type": "code",
      "source_file": "src\\abstracts\\AbstractMap.ts",
      "source_location": "L308"
    },
    {
      "id": "abstractmap_resettypeinference",
      "label": "resetTypeInference()",
      "file_type": "code",
      "source_file": "src\\abstracts\\AbstractMap.ts",
      "source_location": "L359"
    },
    {
      "id": "abstractmap_gettypestring",
      "label": "getTypeString()",
      "file_type": "code",
      "source_file": "src\\abstracts\\AbstractMap.ts",
      "source_location": "L369"
    },
    {
      "id": "abstractmap_haskeyvalidation",
      "label": "hasKeyValidation()",
      "file_type": "code",
      "source_file": "src\\abstracts\\AbstractMap.ts",
      "source_location": "L380"
    },
    {
      "id": "abstractmap_hasvaluevalidation",
      "label": "hasValueValidation()",
      "file_type": "code",
      "source_file": "src\\abstracts\\AbstractMap.ts",
      "source_location": "L388"
    },
    {
      "id": "abstractmap_getkeyvalidationmode",
      "label": "getKeyValidationMode()",
      "file_type": "code",
      "source_file": "src\\abstracts\\AbstractMap.ts",
      "source_location": "L396"
    },
    {
      "id": "abstractmap_getvaluevalidationmode",
      "label": "getValueValidationMode()",
      "file_type": "code",
      "source_file": "src\\abstracts\\AbstractMap.ts",
      "source_location": "L413"
    }
  ],
  "edges": [
    {
      "source": "src_abstracts_abstractmap_ts",
      "target": "src_interfaces",
      "relation": "imports_from",
      "confidence": "EXTRACTED",
      "source_file": "src\\abstracts\\AbstractMap.ts",
      "source_location": "L1",
      "weight": 1.0
    },
    {
      "source": "src_abstracts_abstractmap_ts",
      "target": "zod",
      "relation": "imports_from",
      "confidence": "EXTRACTED",
      "source_file": "src\\abstracts\\AbstractMap.ts",
      "source_location": "L2",
      "weight": 1.0
    },
    {
      "source": "src_abstracts_abstractmap_ts",
      "target": "abstractmap_constructor",
      "relation": "contains",
      "confidence": "EXTRACTED",
      "source_file": "src\\abstracts\\AbstractMap.ts",
      "source_location": "L119",
      "weight": 1.0
    },
    {
      "source": "src_abstracts_abstractmap_ts",
      "target": "abstractmap_length",
      "relation": "contains",
      "confidence": "EXTRACTED",
      "source_file": "src\\abstracts\\AbstractMap.ts",
      "source_location": "L147",
      "weight": 1.0
    },
    {
      "source": "src_abstracts_abstractmap_ts",
      "target": "abstractmap_putall",
      "relation": "contains",
      "confidence": "EXTRACTED",
      "source_file": "src\\abstracts\\AbstractMap.ts",
      "source_location": "L229",
      "weight": 1.0
    },
    {
      "source": "src_abstracts_abstractmap_ts",
      "target": "abstractmap_validatekeytype",
      "relation": "contains",
      "confidence": "EXTRACTED",
      "source_file": "src\\abstracts\\AbstractMap.ts",
      "source_location": "L248",
      "weight": 1.0
    },
    {
      "source": "src_abstracts_abstractmap_ts",
      "target": "abstractmap_validatevaluetype",
      "relation": "contains",
      "confidence": "EXTRACTED",
      "source_file": "src\\abstracts\\AbstractMap.ts",
      "source_location": "L308",
      "weight": 1.0
    },
    {
      "source": "src_abstracts_abstractmap_ts",
      "target": "abstractmap_resettypeinference",
      "relation": "contains",
      "confidence": "EXTRACTED",
      "source_file": "src\\abstracts\\AbstractMap.ts",
      "source_location": "L359",
      "weight": 1.0
    },
    {
      "source": "src_abstracts_abstractmap_ts",
      "target": "abstractmap_gettypestring",
      "relation": "contains",
      "confidence": "EXTRACTED",
      "source_file": "src\\abstracts\\AbstractMap.ts",
      "source_location": "L369",
      "weight": 1.0
    },
    {
      "source": "src_abstracts_abstractmap_ts",
      "target": "abstractmap_haskeyvalidation",
      "relation": "contains",
      "confidence": "EXTRACTED",
      "source_file": "src\\abstracts\\AbstractMap.ts",
      "source_location": "L380",
      "weight": 1.0
    },
    {
      "source": "src_abstracts_abstractmap_ts",
      "target": "abstractmap_hasvaluevalidation",
      "relation": "contains",
      "confidence": "EXTRACTED",
      "source_file": "src\\abstracts\\AbstractMap.ts",
      "source_location": "L388",
      "weight": 1.0
    },
    {
      "source": "src_abstracts_abstractmap_ts",
      "target": "abstractmap_getkeyvalidationmode",
      "relation": "contains",
      "confidence": "EXTRACTED",
      "source_file": "src\\abstracts\\AbstractMap.ts",
      "source_location": "L396",
      "weight": 1.0
    },
    {
      "source": "src_abstracts_abstractmap_ts",
      "target": "abstractmap_getvaluevalidationmode",
      "relation": "contains",
      "confidence": "EXTRACTED",
      "source_file": "src\\abstracts\\AbstractMap.ts",
      "source_location": "L413",
      "weight": 1.0
    },
    {
      "source": "abstractmap_validatekeytype",
      "target": "abstractmap_gettypestring",
      "relation": "calls",
      "confidence": "EXTRACTED",
      "source_file": "src\\abstracts\\AbstractMap.ts",
      "source_location": "L285",
      "weight": 1.0
    },
    {
      "source": "abstractmap_validatevaluetype",
      "target": "abstractmap_gettypestring",
      "relation": "calls",
      "confidence": "EXTRACTED",
      "source_file": "src\\abstracts\\AbstractMap.ts",
      "source_location": "L345",
      "weight": 1.0
    }
  ],
  "raw_calls": [
    {
      "caller_nid": "abstractmap_length",
      "callee": "size",
      "source_file": "src\\abstracts\\AbstractMap.ts",
      "source_location": "L148"
    },
    {
      "caller_nid": "abstractmap_putall",
      "callee": "entries",
      "source_file": "src\\abstracts\\AbstractMap.ts",
      "source_location": "L230"
    },
    {
      "caller_nid": "abstractmap_putall",
      "callee": "put",
      "source_file": "src\\abstracts\\AbstractMap.ts",
      "source_location": "L232"
    },
    {
      "caller_nid": "abstractmap_validatekeytype",
      "callee": "parse",
      "source_file": "src\\abstracts\\AbstractMap.ts",
      "source_location": "L257"
    },
    {
      "caller_nid": "abstractmap_validatekeytype",
      "callee": "join",
      "source_file": "src\\abstracts\\AbstractMap.ts",
      "source_location": "L260"
    },
    {
      "caller_nid": "abstractmap_validatekeytype",
      "callee": "map",
      "source_file": "src\\abstracts\\AbstractMap.ts",
      "source_location": "L260"
    },
    {
      "caller_nid": "abstractmap_validatekeytype",
      "callee": "keyValidator",
      "source_file": "src\\abstracts\\AbstractMap.ts",
      "source_location": "L275"
    },
    {
      "caller_nid": "abstractmap_validatekeytype",
      "callee": "size",
      "source_file": "src\\abstracts\\AbstractMap.ts",
      "source_location": "L284"
    },
    {
      "caller_nid": "abstractmap_validatevaluetype",
      "callee": "parse",
      "source_file": "src\\abstracts\\AbstractMap.ts",
      "source_location": "L317"
    },
    {
      "caller_nid": "abstractmap_validatevaluetype",
      "callee": "join",
      "source_file": "src\\abstracts\\AbstractMap.ts",
      "source_location": "L320"
    },
    {
      "caller_nid": "abstractmap_validatevaluetype",
      "callee": "map",
      "source_file": "src\\abstracts\\AbstractMap.ts",
      "source_location": "L320"
    },
    {
      "caller_nid": "abstractmap_validatevaluetype",
      "callee": "valueValidator",
      "source_file": "src\\abstracts\\AbstractMap.ts",
      "source_location": "L335"
    },
    {
      "caller_nid": "abstractmap_validatevaluetype",
      "callee": "size",
      "source_file": "src\\abstracts\\AbstractMap.ts",
      "source_location": "L344"
    },
    {
      "caller_nid": "abstractmap_gettypestring",
      "callee": "isArray",
      "source_file": "src\\abstracts\\AbstractMap.ts",
      "source_location": "L372"
    }
  ]
}
